mkdocs_matplotlib/__init__.py
mkdocs_matplotlib/plugin.py
mkdocs_matplotlib-0.10.1.dist-info/entry_points.txt
mkdocs_matplotlib-0.10.1.dist-info/WHEEL
mkdocs_matplotlib-0.10.1.dist-info/METADATA
mkdocs_matplotlib-0.10.1.dist-info/RECORD
