Metadata-Version: 2.1
Name: mkdocs-matplotlib
Version: 0.10.1
Summary: Live rendering of python code using matplotlib
Home-page: https://mkdocs-matplotlib.readthedocs.io/en/latest/
License: MIT
Keywords: mkdocs,matplotlib,documentation
Author: An Hoang
Author-email: an.hoang@statworx.com
Requires-Python: >=3.8,<4.0
Classifier: License :: OSI Approved :: MIT License
Classifier: Programming Language :: Python :: 3
Classifier: Programming Language :: Python :: 3.10
Classifier: Programming Language :: Python :: 3.8
Classifier: Programming Language :: Python :: 3.9
Requires-Dist: beautifulsoup4 (>=4.7.1)
Requires-Dist: markdown (!=3.3.5)
Requires-Dist: mkdocs (>=1.1.1)
Requires-Dist: mkdocs-material (>=8.1.9)
Requires-Dist: psutil (>=5.9.1)
Requires-Dist: seaborn (>=0.10.0)
Project-URL: Documentation, https://mkdocs-matplotlib.readthedocs.io/en/latest/
Project-URL: Repository, https://github.com/AnHo4ng/mkdocs-matplotlib
